[
 {
  "count": 1,
  "name": "NIT Calicut - National Institute of Technology",
  "place": "Calicut",
  "type": "Govt",
  "contact": "nitc.ac.in"
 },
 {
  "count": 2,
  "name": "IIST - Indian Institute of Space Science and Technology",
  "place": "Thiruvananthapuram",
  "type": "Govt",
  "contact": "iist.ac.in"
 },
 {
  "count": 3,
  "name": "Amrita School of Engineering, Amrita Vishwa Vidyapeetham - Amritapuri Campus",
  "place": "Amritapuri",
  "type": "Pvt",
  "contact": ""
 },
 {
  "count": 4,
  "name": "IIT Palakkad - Indian Institute of Technology",
  "place": "Palakkad",
  "type": "Govt",
  "contact": "iitpkd.ac.in"
 },
 {
  "count": 5,
  "name": "College of Engineering, Trivandrum",
  "place": "Thiruvananthapuram",
  "type": "Govt",
  "contact": "cet.ac.in"
 },
 {
  "count": 6,
  "name": "RSET - Rajagiri School of Engineering and Technology",
  "place": "Kochi",
  "type": "Pvt",
  "contact": "rajagiritech.ac.in"
 },
 {
  "count": 7,
  "name": "Government Engineering College, Thrissur",
  "place": "Thrissur",
  "type": "Govt",
  "contact": "gectcr.ac.in"
 },
 {
  "count": 8,
  "name": "Cochin University of Science and Technology, Kochi",
  "place": "Kochi",
  "type": "Govt",
  "contact": "cusat.ac.in"
 },
 {
  "count": 9,
  "name": "MEC Kochi - Government Model Engineering College",
  "place": "Kochi",
  "type": "Govt",
  "contact": "mec.ac.in"
 },
 {
  "count": 10,
  "name": "TKM Institute of Management",
  "place": "Kollam",
  "type": "Govt",
  "contact": "tkmce.ac.in"
 },
 {
  "count": 11,
  "name": "Muthoot Institute of Technology and Science",
  "place": "Ernakulum",
  "type": "Pvt",
  "contact": "gmail.com"
 },
 {
  "count": 12,
  "name": "IIIT Kottayam - Indian Institute of Information Technology",
  "place": "Kottayam",
  "type": "",
  "contact": "iiitkottayam.ac.in"
 },
 {
  "count": 13,
  "name": "SCMS School of Engineering and Technology",
  "place": "Ernakulum",
  "type": "Pvt",
  "contact": "scmsgroup.org"
 },
 {
  "count": 14,
  "name": "FISAT - Federal Institute of Science and Technology",
  "place": "Ernakulum",
  "type": "Pvt",
  "contact": "fisat.ac.in"
 },
 {
  "count": 15,
  "name": "Saintgits College of Engineering",
  "place": "Kottayam",
  "type": "Pvt",
  "contact": "saintgits.org"
 },
 {
  "count": 16,
  "name": "College of Engineering, Chengannur",
  "place": "Kerala - Other",
  "type": "Govt",
  "contact": "ceconline.edu"
 },
 {
  "count": 17,
  "name": "St. Joseph College of Engineering and Technology",
  "place": "Kottayam",
  "type": "Pvt",
  "contact": "sancharnet.in"
 },
 {
  "count": 18,
  "name": "Vedavyasa Institute of Technology",
  "place": "Kerala - Other",
  "type": "Pvt",
  "contact": "vedavyasa.org"
 },
 {
  "count": 19,
  "name": "Mohandas College of Engineering and Technology",
  "place": "Thiruvananthapuram",
  "type": "Pvt",
  "contact": "mcetonline.com"
 },
 {
  "count": 20,
  "name": "NSS College of Engineering",
  "place": "Palakkad",
  "type": "Govt",
  "contact": "nssce.ac.in"
 },
 {
  "count": 21,
  "name": "Sree Chitra Thirunal College of Engineering",
  "place": "Thiruvananthapuram",
  "type": "Govt",
  "contact": "sctce.ac.in"
 },
 {
  "count": 22,
  "name": "Cochin University College of Engineering Kuttanad, Cochin University of Science and Technology, Kochi",
  "place": "Kerala - Other",
  "type": "Govt",
  "contact": "cusat.ac.in"
 },
 {
  "count": 23,
  "name": "Mar Athanasius College of Engineering",
  "place": "Kerala - Other",
  "type": "Pvt",
  "contact": "mace.ac.in"
 },
 {
  "count": 24,
  "name": "RIET - Rajadhani Institute of Engineering and Technology",
  "place": "Trivandrum",
  "type": "Pvt",
  "contact": "rajadhanimail.com"
 },
 {
  "count": 25,
  "name": "Amal Jyothi College of Engineering",
  "place": "Kottayam",
  "type": "Pvt",
  "contact": "amaljyothi.ac.in"
 },
 {
  "count": 26,
  "name": "Mar Baselios College of Engineering and Technology",
  "place": "Thiruvananthapuram",
  "type": "Pvt",
  "contact": "gmail.com"
 },
 {
  "count": 27,
  "name": "Rajiv Gandhi Institute of Technology, Kerala",
  "place": "Kottayam",
  "type": "Govt",
  "contact": "rit.ac.in"
 },
 {
  "count": 28,
  "name": "Adi Shankara Institute of Engineering and Technology",
  "place": "Ernakulum",
  "type": "Pvt",
  "contact": "adishankara.ac.in"
 },
 {
  "count": 29,
  "name": "Government Engineering College, Barton Hill",
  "place": "Thiruvananthapuram",
  "type": "Govt",
  "contact": "gecbh.ac.in"
 },
 {
  "count": 30,
  "name": "TOMS College of Engineering and Polytechnic",
  "place": "Kottayam",
  "type": "Pvt",
  "contact": "toms.ac.in"
 },
 {
  "count": 31,
  "name": "Government Engineering College, Sreekrishnapuram",
  "place": "Palakkad",
  "type": "Govt",
  "contact": "gecskp.ac.in"
 },
 {
  "count": 32,
  "name": "Government College of Engineering, Kannur",
  "place": "Kannur",
  "type": "Govt",
  "contact": "gcek.ac.in"
 },
 {
  "count": 33,
  "name": "TIST - Toc H Institute of Science \u0026 Technology",
  "place": "Ernakulum",
  "type": "Pvt",
  "contact": "tistcochin.edu.in"
 },
 {
  "count": 34,
  "name": "Indian Naval Academy",
  "place": "Kannur",
  "type": "Govt",
  "contact": "navy.gov.in"
 },
 {
  "count": 35,
  "name": "Thangal Kunju Musaliar Institute of Technology",
  "place": "Kollam",
  "type": "Pvt",
  "contact": "gmail.com"
 },
 {
  "count": 36,
  "name": "Sahrdaya College of Engineering and Technology (SCET)",
  "place": "Thrissur",
  "type": "Pvt",
  "contact": "sahrdaya.ac.in"
 },
 {
  "count": 37,
  "name": "Jyothi Engineering College",
  "place": "Thrissur",
  "type": "Pvt",
  "contact": "jecc.ac.in"
 },
 {
  "count": 38,
  "name": "Government Engineering College, Kozhikode",
  "place": "Kozhikode",
  "type": "Govt",
  "contact": ""
 },
 {
  "count": 39,
  "name": "College of Engineering, Thalassery",
  "place": "Kannur",
  "type": "Govt",
  "contact": ""
 },
 {
  "count": 40,
  "name": "LBS College of Engineering",
  "place": "Kasargode",
  "type": "Govt",
  "contact": "lbscek.ac.in"
 },
 {
  "count": 41,
  "name": "LBS Institute of Technology for Women",
  "place": "Thiruvananthapuram",
  "type": "Govt",
  "contact": ""
 },
 {
  "count": 42,
  "name": "VJCET - Viswajyothi College of Engineering and Technology",
  "place": "Ernakulum",
  "type": "",
  "contact": "vjcet.org"
 },
 {
  "count": 43,
  "name": "College of Engineering, Adoor",
  "place": "Kerala - Other",
  "type": "Govt",
  "contact": "ihrd.ac.in"
 },
 {
  "count": 44,
  "name": "Government Engineering College, Idukki",
  "place": "Idukki",
  "type": "Govt",
  "contact": ""
 },
 {
  "count": 45,
  "name": "Nehru College of Engineering and Research Centre (NCERC)",
  "place": "Thrissur",
  "type": "Pvt",
  "contact": "ncerc.ac.in"
 },
 {
  "count": 46,
  "name": "University College of Engineering, Kariavattom",
  "place": "Thiruvananthapuram",
  "type": "Govt",
  "contact": ""
 },
 {
  "count": 47,
  "name": "MES College of Engineering",
  "place": "Malappuram",
  "type": "Pvt",
  "contact": "mescoepune.org"
 },
 {
  "count": 48,
  "name": "College of Engineering Perumon",
  "place": "Kollam",
  "type": "Govt",
  "contact": ""
 },
 {
  "count": 49,
  "name": "VAST - Vidya Academy Of Science And Technology",
  "place": "Thrissur",
  "type": "Pvt",
  "contact": "vidyaacademy.ac.in"
 },
 {
  "count": 50,
  "name": "CCE - Christ College Of Engineering",
  "place": "Thrissur",
  "type": "Pvt",
  "contact": "cce.edu.in"
 },
 {
  "count": 51,
  "name": "Sree Narayana Gurukulam College Of Engineering - SNGCE",
  "place": "Ernakulum",
  "type": "Pvt",
  "contact": "sngce.ac.in"
 },
 {
  "count": 52,
  "name": "College of Engineering Vadakara",
  "place": "Kozhikode",
  "type": "Govt",
  "contact": "gmail.com"
 },
 {
  "count": 53,
  "name": "College of Engineering, Attingal",
  "place": "Thiruvananthapuram",
  "type": "Govt",
  "contact": ""
 },
 {
  "count": 54,
  "name": "Government Engineering College, Mananthavady",
  "place": "Wayanad",
  "type": "Govt",
  "contact": ""
 },
 {
  "count": 55,
  "name": "Marian Engineering College",
  "place": "Thiruvananthapuram",
  "type": "Pvt",
  "contact": "marian.ac.in"
 },
 {
  "count": 56,
  "name": "Kerala Veterinary and Animal Sciences University",
  "place": "Wayanad",
  "type": "Govt",
  "contact": "kvasu.ac.in"
 },
 {
  "count": 57,
  "name": "Vimal Jyoti Engineering College - VJEC",
  "place": "Kannur",
  "type": "Pvt",
  "contact": "vjec.ac.in"
 },
 {
  "count": 58,
  "name": "College of Engineering, Kallooppara",
  "place": "Pathanamthitta",
  "type": "Govt",
  "contact": ""
 },
 {
  "count": 59,
  "name": "MGU Kerala - Mahatma Gandhi University",
  "place": "Kottayam",
  "type": "Govt",
  "contact": "mgu.ac.in"
 },
 {
  "count": 60,
  "name": "College of Engineering, Munnar",
  "place": "Munnar",
  "type": "Govt",
  "contact": ""
 },
 {
  "count": 61,
  "name": "Sree Buddha College of Engineering (SBCE)",
  "place": "Kerala - Other",
  "type": "Pvt",
  "contact": "hotmail.com"
 },
 {
  "count": 62,
  "name": "College of Engineering, Cherthala",
  "place": "Kerala - Other",
  "type": "Govt",
  "contact": ""
 },
 {
  "count": 63,
  "name": "College of Engineering, Muttathara",
  "place": "Thiruvananthapuram",
  "type": "Govt",
  "contact": "gmail.com"
 },
 {
  "count": 64,
  "name": "ACE College of Engineering",
  "place": "Thiruvananthapuram",
  "type": "Pvt",
  "contact": "acetvm.com"
 },
 {
  "count": 65,
  "name": "KMCT College of Engineering",
  "place": "Kozhikode",
  "type": "Pvt",
  "contact": ""
 },
 {
  "count": 66,
  "name": "SJCET - St. Joseph'S College of Engineering and Technology",
  "place": "Kottayam",
  "type": "Pvt",
  "contact": "sjcetpalai.ac.in"
 },
 {
  "count": 67,
  "name": "College of Engineering, Kidangoor",
  "place": "Kottayam",
  "type": "Govt",
  "contact": ""
 },
 {
  "count": 68,
  "name": "College of Engineering, Trikaripur",
  "place": "Kasargode",
  "type": "Govt",
  "contact": "cetkr.ac.in"
 },
 {
  "count": 69,
  "name": "University College of Engineering, Thodupuzha",
  "place": "Idukki",
  "type": "Pvt",
  "contact": "ucet.ac.in"
 },
 {
  "count": 70,
  "name": "College of Engineering, Karunagappally",
  "place": "Kollam",
  "type": "Govt",
  "contact": ""
 },
 {
  "count": 71,
  "name": "Kelappaji College of Agricultural Engineering and Technology",
  "place": "Kerala - Other",
  "type": "Govt",
  "contact": "kau.in"
 },
 {
  "count": 72,
  "name": "AISAT - Albertian Institute of Science \u0026 Technology",
  "place": "Kochi",
  "type": "Pvt",
  "contact": "aisat.ac.in"
 },
 {
  "count": 73,
  "name": "Sahrdaya College of Engineering and Technology",
  "place": "Thrissur",
  "type": "Pvt",
  "contact": ""
 },
 {
  "count": 74,
  "name": "College of Engineering And Management, Punnapra",
  "place": "Kerala - Other",
  "type": "Govt",
  "contact": ""
 },
 {
  "count": 75,
  "name": "Jawaharlal College of Engineering and Technology",
  "place": "Palakkad",
  "type": "Pvt",
  "contact": "nehrucolleges.com"
 },
 {
  "count": 76,
  "name": "St. Thomas College of Engineering and Technology, Chengannoor",
  "place": "Kerala - Other",
  "type": "Pvt",
  "contact": "stcet.net"
 },
 {
  "count": 77,
  "name": "Mangalam College of Engineering - MCE",
  "place": "Kottayam",
  "type": "Pvt",
  "contact": "mangalam.in"
 },
 {
  "count": 78,
  "name": "Providence College of Engineering - PCE",
  "place": "Kerala - Other",
  "type": "Pvt",
  "contact": "providence.edu.in"
 },
 {
  "count": 79,
  "name": "Thangal Kunju Musaliar Institute of Technology",
  "place": "Kollam",
  "type": "Pvt",
  "contact": ""
 },
 {
  "count": 80,
  "name": "Indira Gandhi Institute of Engineering \u0026 Technology, Kothamangalam",
  "place": "Ernakulum",
  "type": "Govt",
  "contact": ""
 },
 {
  "count": 81,
  "name": "MEA Engineering College (MEA Kerala)",
  "place": "Kerala - Other",
  "type": "Pvt",
  "contact": "meaengg.in"
 },
 {
  "count": 82,
  "name": "Royal College of Engineering and Technology",
  "place": "Kerala - Other",
  "type": "Pvt",
  "contact": ""
 },
 {
  "count": 83,
  "name": "KTU - APJ Abdul Kalam Technological University",
  "place": "Thiruvananthapuram",
  "type": "Govt",
  "contact": "ktu.edu.in"
 },
 {
  "count": 84,
  "name": "Kelappaji College of Agricultural Engineering and Technology, Kerala Agricultural University",
  "place": "Malappuram",
  "type": "Govt",
  "contact": "kau.in"
 },
 {
  "count": 85,
  "name": "Mount Zion College of Engineering (MZCE Pathanamthitta)",
  "place": "Pathanamthitta",
  "type": "Pvt",
  "contact": ""
 },
 {
  "count": 86,
  "name": "Nirmala College of Engineering",
  "place": "Thrissur",
  "type": "Pvt",
  "contact": "nirmalacollege.in"
 },
 {
  "count": 87,
  "name": "Kerala University of Fisheries and Ocean Studies",
  "place": "Kochi",
  "type": "Govt",
  "contact": ""
 },
 {
  "count": 88,
  "name": "College of Engineering, Aranmula",
  "place": "Pathanamthitta",
  "type": "Govt",
  "contact": ""
 },
 {
  "count": 89,
  "name": "IES College of Engineering",
  "place": "Thrissur",
  "type": "Pvt",
  "contact": ""
 },
 {
  "count": 90,
  "name": "Mar Baselios Institute of Technology And Science, Kothamangalam",
  "place": "Ernakulum",
  "type": "Pvt",
  "contact": ""
 },
 {
  "count": 91,
  "name": "College of Engineering, Pathanapuram",
  "place": "Kerala - Other",
  "type": "Govt",
  "contact": ""
 },
 {
  "count": 92,
  "name": "Sreepathy Institute of Management and Technology",
  "place": "Palakkad",
  "type": "Pvt",
  "contact": "gmail.com"
 },
 {
  "count": 93,
  "name": "ILAHIA College of Engineering and Technology",
  "place": "Kerala - Other",
  "type": "Pvt",
  "contact": "gmail.com"
 },
 {
  "count": 94,
  "name": "College of Engineering, Kottarakkara",
  "place": "Kollam",
  "type": "Govt",
  "contact": ""
 },
 {
  "count": 95,
  "name": "Christ Knowledge City",
  "place": "Kochi",
  "type": "Pvt",
  "contact": "christknowledgecity.com"
 },
 {
  "count": 96,
  "name": "College of Dairy Science and Technology, Mannuthy - Kerala Veterinary and Animal Sciences University",
  "place": "Thrissur",
  "type": "Govt",
  "contact": "kvasu.ac.in"
 },
 {
  "count": 97,
  "name": "Jai Bharath College of Management And Engineering Technology",
  "place": "Kerala - Other",
  "type": "Pvt",
  "contact": ""
 },
 {
  "count": 98,
  "name": "Muslim Association College of Engineering, Venjaramoodu",
  "place": "Thiruvananthapuram",
  "type": "Pvt",
  "contact": ""
 },
 {
  "count": 99,
  "name": "AWH Engineering College",
  "place": "Calicut",
  "type": "Pvt",
  "contact": "awhengg.org"
 },
 {
  "count": 100,
  "name": "Carmel College of Engineering And Technology, Alappuzha",
  "place": "Kerala - Other",
  "type": "Pvt",
  "contact": ""
 },
 {
  "count": 101,
  "name": "Malabar College of Engineering \u0026 Technology, Wadakancherry",
  "place": "Thrissur",
  "type": "Pvt",
  "contact": ""
 },
 {
  "count": 102,
  "name": "Thejus Engineering College",
  "place": "Thrissur",
  "type": "Pvt",
  "contact": "thejusengg.com"
 },
 {
  "count": 103,
  "name": "VISAT Engineering College, Elanji",
  "place": "Kerala - Other",
  "type": "Pvt",
  "contact": "visat.ac.in"
 },
 {
  "count": 104,
  "name": "Mentor Academy for Design Entrepreneurship Innovation and Technology",
  "place": "Ernakulum",
  "type": "",
  "contact": ""
 },
 {
  "count": 105,
  "name": "ICCS College of Engineering and Management",
  "place": "Thrissur",
  "type": "Pvt",
  "contact": ""
 },
 {
  "count": 106,
  "name": "Universal Engineering College",
  "place": "Thrissur",
  "type": "Pvt",
  "contact": "universalcollege.net"
 },
 {
  "count": 107,
  "name": "Cochin Institute of Science and Technology",
  "place": "Ernakulum",
  "type": "Pvt",
  "contact": "cochinisat.ac.in"
 },
 {
  "count": 108,
  "name": "Mahaguru Institute of Technology",
  "place": "Alleppey",
  "type": "Pvt",
  "contact": ""
 },
 {
  "count": 109,
  "name": "Younus College of Engineering and Technology",
  "place": "Kollam",
  "type": "Pvt",
  "contact": "gmail.com"
 },
 {
  "count": 110,
  "name": "St. Thomas College of Engineering and Technology, Kannur",
  "place": "Kannur",
  "type": "",
  "contact": ""
 },
 {
  "count": 111,
  "name": "Sarabhai Institute of Science and Technology",
  "place": "Trivandrum",
  "type": "Pvt",
  "contact": "sist.in"
 },
 {
  "count": 112,
  "name": "SNGIST - Sree Narayana Guru Institute of Science and Technology",
  "place": "Ernakulum",
  "type": "Pvt",
  "contact": "sngist.org"
 },
 {
  "count": 113,
  "name": "KMCT College of Engineering for Women",
  "place": "Kozhikode",
  "type": "Pvt",
  "contact": ""
 },
 {
  "count": 114,
  "name": "Holy Grace Academy of Engineering, Thrissur",
  "place": "Thrissur",
  "type": "Pvt",
  "contact": ""
 },
 {
  "count": 115,
  "name": "LMCST: Lourdes Matha College of Science and Technology",
  "place": "Thiruvananthapuram",
  "type": "Pvt",
  "contact": "gmail.com"
 },
 {
  "count": 116,
  "name": "MET'S School of Engineering, Mala",
  "place": "Kerala - Other",
  "type": "Pvt",
  "contact": ""
 },
 {
  "count": 117,
  "name": "College of Engineering, Poonjar",
  "place": "Kottayam",
  "type": "Govt",
  "contact": ""
 },
 {
  "count": 118,
  "name": "ASET - Ahalia School of Engineering \u0026 Technology",
  "place": "Kerala - Other",
  "type": "Pvt",
  "contact": "ahalia.edu.in"
 },
 {
  "count": 119,
  "name": "Musaliar College of Engineering, Chirayinkeezh",
  "place": "Trivandrum",
  "type": "Pvt",
  "contact": ""
 },
 {
  "count": 120,
  "name": "Al-Ameen Engineering College",
  "place": "Palakkad",
  "type": "Pvt",
  "contact": "alameencollege.com"
 },
 {
  "count": 121,
  "name": "St. Thomas Institute for Science and Technology",
  "place": "Trivandrum",
  "type": "Pvt",
  "contact": "gmail.com"
 },
 {
  "count": 122,
  "name": "Heera College of Engineering \u0026 Technology",
  "place": "Thiruvananthapuram",
  "type": "Pvt",
  "contact": ""
 },
 {
  "count": 123,
  "name": "UKF College of Engineering And Technology, Parippally",
  "place": "Kollam",
  "type": "Pvt",
  "contact": ""
 },
 {
  "count": 124,
  "name": "Baselios Mathews II College of Engineering",
  "place": "Kollam",
  "type": "Pvt",
  "contact": "bmce.ac.in"
 },
 {
  "count": 125,
  "name": "M.Dasan Institute Of Technology, Kozhikode",
  "place": "Kozhikode",
  "type": "Pvt",
  "contact": ""
 },
 {
  "count": 126,
  "name": "ILM College of Engineering and Technology, Ernakulam",
  "place": "Ernakulum",
  "type": "Pvt",
  "contact": ""
 },
 {
  "count": 127,
  "name": "Mar Baselios Christian College of Engineering And Technology",
  "place": "Idukki",
  "type": "Pvt",
  "contact": ""
 },
 {
  "count": 128,
  "name": "K M E A Engineering College, Edathala",
  "place": "Kerala - Other",
  "type": "Pvt",
  "contact": ""
 },
 {
  "count": 129,
  "name": "Sree Narayana Institute of Technology, Adoor",
  "place": "Pathanamthitta",
  "type": "Pvt",
  "contact": ""
 },
 {
  "count": 130,
  "name": "MGM College of Engineering And Technology, Ernakulam",
  "place": "Ernakulum",
  "type": "Pvt",
  "contact": "mgmcet.ac.in"
 },
 {
  "count": 131,
  "name": "Al Azhar College of Engineering and Technology",
  "place": "Idukki",
  "type": "Pvt",
  "contact": ""
 },
 {
  "count": 132,
  "name": "Musaliar College of Engineering \u0026 Technology, Pathanamthitta",
  "place": "Pathanamthitta",
  "type": "Pvt",
  "contact": ""
 },
 {
  "count": 133,
  "name": "Matha College of Technology",
  "place": "Ernakulum",
  "type": "Pvt",
  "contact": "gmail.com"
 },
 {
  "count": 134,
  "name": "Sree Narayana Guru College of Engineering And Technology",
  "place": "Kannur",
  "type": "Pvt",
  "contact": ""
 },
 {
  "count": 135,
  "name": "Bishop Jerome Institute",
  "place": "Kollam",
  "type": "Pvt",
  "contact": "yahoo.com"
 },
 {
  "count": 136,
  "name": "Axis College of Engineering and Technology",
  "place": "Thrissur",
  "type": "Pvt",
  "contact": ""
 },
 {
  "count": 137,
  "name": "MGM College of Engineering and Pharmaceutical Sciences",
  "place": "Malappuram",
  "type": "Pvt",
  "contact": ""
 },
 {
  "count": 138,
  "name": "College of Dairy Science and Technology, Thiruvananthapuram - Kerala Veterinary and Animal Sciences University",
  "place": "Thiruvananthapuram",
  "type": "Govt",
  "contact": "kvasu.ac.in"
 },
 {
  "count": 139,
  "name": "Hindustan College of Engineering, Kulathupuzha",
  "place": "Kollam",
  "type": "Govt",
  "contact": ""
 },
 {
  "count": 140,
  "name": "Rajadhani Institute of Science and Technology",
  "place": "Palakkad",
  "type": "Pvt",
  "contact": ""
 },
 {
  "count": 141,
  "name": "Indira Gandhi Institute of Polytechnic and Engineering",
  "place": "Ernakulum",
  "type": "Pvt",
  "contact": ""
 },
 {
  "count": 142,
  "name": "University Institute of Technology, Alappuzha",
  "place": "Alleppey",
  "type": "Govt",
  "contact": "gmail.com"
 },
 {
  "count": 143,
  "name": "Amaljyothi College of Engineering",
  "place": "Kottayam",
  "type": "Pvt",
  "contact": "amaljyothi.ac.in"
 },
 {
  "count": 144,
  "name": "Eranad Knowledge City",
  "place": "Malappuram",
  "type": "Pvt",
  "contact": ""
 },
 {
  "count": 145,
  "name": "MES College of Engineering \u0026 Technology, Ernakulam",
  "place": "Ernakulum",
  "type": "Pvt",
  "contact": ""
 },
 {
  "count": 146,
  "name": "MES Institute of Technology And Management, Chathannoor",
  "place": "Kollam",
  "type": "Pvt",
  "contact": ""
 },
 {
  "count": 147,
  "name": "ACE - Ammini College of Engineering",
  "place": "Palakkad",
  "type": "Pvt",
  "contact": "ammini.edu.in"
 },
 {
  "count": 148,
  "name": "Cochin College of Engineering and Technology, Malappuram",
  "place": "Malappuram",
  "type": "Pvt",
  "contact": ""
 },
 {
  "count": 149,
  "name": "P.A. Aziz College of Engineering and Technology",
  "place": "Thiruvananthapuram",
  "type": "Pvt",
  "contact": ""
 },
 {
  "count": 150,
  "name": "Kottayam Institute of Technology And Science, Kottayam",
  "place": "Kottayam",
  "type": "Pvt",
  "contact": ""
 },
 {
  "count": 151,
  "name": "Euro Tech Maritime Academy",
  "place": "Ernakulum",
  "type": "Pvt",
  "contact": "eurotechmaritime.org"
 },
 {
  "count": 152,
  "name": "Trinity College of Engineering",
  "place": "Thiruvananthapuram",
  "type": "Pvt",
  "contact": "gmail.com"
 },
 {
  "count": 153,
  "name": "Skiltek Group of Institutions",
  "place": "Kochi",
  "type": "Pvt",
  "contact": "skiltek.in"
 },
 {
  "count": 154,
  "name": "Sree Sankara College",
  "place": "Ernakulum",
  "type": "Pvt",
  "contact": "ssc.edu.in"
 },
 {
  "count": 155,
  "name": "John Cox Memorial CSI Institute of Technology, Thiruvananthapuram",
  "place": "Thiruvananthapuram",
  "type": "Pvt",
  "contact": ""
 },
 {
  "count": 156,
  "name": "TKM School of Architecture,Kollam",
  "place": "Kollam",
  "type": "Pvt",
  "contact": ""
 },
 {
  "count": 157,
  "name": "St.Thomas College of Engineering and Technology",
  "place": "Alleppey",
  "type": "Pvt",
  "contact": ""
 },
 {
  "count": 158,
  "name": "Al-Azhar College of Engineering and Polytechnic",
  "place": "Idukki",
  "type": "Pvt",
  "contact": ""
 },
 {
  "count": 159,
  "name": "Travancore Engineering College",
  "place": "Kollam",
  "type": "Pvt",
  "contact": ""
 },
 {
  "count": 160,
  "name": "SNM Institute of Management and Technology",
  "place": "Ernakulum",
  "type": "Pvt",
  "contact": ""
 },
 {
  "count": 161,
  "name": "Vidya Academy of Science and Technology, Technical Campus",
  "place": "Thiruvananthapuram",
  "type": "Pvt",
  "contact": ""
 },
 {
  "count": 162,
  "name": "Sree Ernakulathappan college of engineering and Management",
  "place": "Kerala - Other",
  "type": "Pvt",
  "contact": ""
 },
 {
  "count": 163,
  "name": "M G College of Engineering, Thiruvallom",
  "place": "Thiruvananthapuram",
  "type": "Pvt",
  "contact": ""
 },
 {
  "count": 164,
  "name": "Gurudeva Institute of Science \u0026 Technology, Puthuppally",
  "place": "Kottayam",
  "type": "Pvt",
  "contact": ""
 },
 {
  "count": 165,
  "name": "Baselios Thomas I Catholicose College of Engineering and Technology, BTC",
  "place": "Kerala - Other",
  "type": "Pvt",
  "contact": "btcc.ac.in"
 },
 {
  "count": 166,
  "name": "PRS College of Engineering And Technology",
  "place": "Trivandrum",
  "type": "Pvt",
  "contact": ""
 },
 {
  "count": 167,
  "name": "Sree Vellappally Natesan College of Engineering, Mavelikkara",
  "place": "Kerala - Other",
  "type": "Pvt",
  "contact": ""
 },
 {
  "count": 168,
  "name": "College of Engineering and Technology, Payyannur",
  "place": "Kannur",
  "type": "Pvt",
  "contact": ""
 },
 {
  "count": 169,
  "name": "Valia Koonambaikulathamma College of Engineering And technology",
  "place": "Kerala - Other",
  "type": "",
  "contact": ""
 },
 {
  "count": 170,
  "name": "University College of Engineering",
  "place": "Idukki",
  "type": "Govt",
  "contact": ""
 },
 {
  "count": 171,
  "name": "College of Dairy Science and Technology, Idukki - Kerala Veterinary and Animal Sciences University",
  "place": "Idukki",
  "type": "Govt",
  "contact": "kvasu.ac.in"
 },
 {
  "count": 172,
  "name": "Malabar Institute of Technology, Anjarakandi",
  "place": "Kannur",
  "type": "Pvt",
  "contact": ""
 },
 {
  "count": 173,
  "name": "KVM College of Engineering and IT",
  "place": "Kerala - Other",
  "type": "Pvt",
  "contact": "kvmce.in"
 },
 {
  "count": 174,
  "name": "KMCT College of Engineering for Emerging Technology",
  "place": "Kozhikode",
  "type": "",
  "contact": "kmct.edu.in"
 },
 {
  "count": 175,
  "name": "Believers Church Caarmel Engineering College",
  "place": "Pathanamthitta",
  "type": "Pvt",
  "contact": "bccaarmel.ac.in"
 },
 {
  "count": 176,
  "name": "Aryanet Institute of Technology(AIT, Palakkad)",
  "place": "Kerala - Other",
  "type": "Pvt",
  "contact": ""
 },
 {
  "count": 177,
  "name": "Shahul Hameed Memorial Engineering College",
  "place": "Kollam",
  "type": "Pvt",
  "contact": ""
 },
 {
  "count": 178,
  "name": "Sree Buddha College of Engineering, Ayathil",
  "place": "Pathanamthitta",
  "type": "Pvt",
  "contact": ""
 },
 {
  "count": 179,
  "name": "College of Engineering and Technology,Kannur",
  "place": "Kannur",
  "type": "Pvt",
  "contact": "gmail.com"
 },
 {
  "count": 180,
  "name": "College of Applied Sciences, Malappuram",
  "place": "Malappuram",
  "type": "Govt",
  "contact": "gmail.com"
 },
 {
  "count": 181,
  "name": "Younus Institute of Technology",
  "place": "Kollam",
  "type": "Pvt",
  "contact": "yit.ac.in"
 },
 {
  "count": 182,
  "name": "Mount Zion Institute of Science \u0026 Tehnology, Chengannur",
  "place": "Kerala - Other",
  "type": "Pvt",
  "contact": ""
 },
 {
  "count": 183,
  "name": "Focus Institute of Science and Technology",
  "place": "Thrissur",
  "type": "Pvt",
  "contact": "focuscampus.org"
 },
 {
  "count": 184,
  "name": "Sadguru Swamy Nithyananda Institute of Technology",
  "place": "Kasargode",
  "type": "Pvt",
  "contact": ""
 },
 {
  "count": 185,
  "name": "ILAHIA School of Science and Technology",
  "place": "Ernakulum",
  "type": "Pvt",
  "contact": ""
 },
 {
  "count": 186,
  "name": "KR Gouri Amma College of Engineering",
  "place": "Kerala - Other",
  "type": "Pvt",
  "contact": ""
 },
 {
  "count": 187,
  "name": "Institute of Engineering and Technology, University of Calicut",
  "place": "Malappuram",
  "type": "",
  "contact": ""
 },
 {
  "count": 188,
  "name": "Archana College of Engineering",
  "place": "Kerala - Other",
  "type": "Pvt",
  "contact": "gmail.com"
 },
 {
  "count": 189,
  "name": "College of Pharmaceutical Sciences, Thiruvananthapuram",
  "place": "Thiruvananthapuram",
  "type": "Govt",
  "contact": ""
 },
 {
  "count": 190,
  "name": "Layola Institute of Science and Technology",
  "place": "Thrissur",
  "type": "",
  "contact": ""
 },
 {
  "count": 191,
  "name": "North Malabar Institute  of Technology, Kanhangad",
  "place": "Kasargode",
  "type": "Pvt",
  "contact": "nmitkerala.ac.in"
 }
]